longbow/__init__.py
longbow/longbow.py
longbow/model/ecoli_R10D0FAST.csv
longbow/model/ecoli_R10D0HAC.csv
longbow/model/ecoli_R10D0SUP.csv
longbow/model/ecoli_R10G6FAST.csv
longbow/model/ecoli_R10G6HAC.csv
longbow/model/ecoli_R10G6SUP.csv
longbow/model/ecoli_R9D0FAST.csv
longbow/model/ecoli_R9D0HAC.csv
longbow/model/ecoli_R9D0SUP.csv
longbow/model/ecoli_R9G2.csv
longbow/model/ecoli_R9G4FAST.csv
longbow/model/ecoli_R9G4HAC.csv
longbow/model/ecoli_R9G6FAST.csv
longbow/model/ecoli_R9G6HAC.csv
longbow/model/ecoli_R9G6SUP.csv
longbow/model/fish_R10D0FAST.csv
longbow/model/fish_R10D0HAC.csv
longbow/model/fish_R10D0SUP.csv
longbow/model/fish_R10G6FAST.csv
longbow/model/fish_R10G6HAC.csv
longbow/model/fish_R10G6SUP.csv
longbow/model/fruitfly_R10D0FAST.csv
longbow/model/fruitfly_R10D0HAC.csv
longbow/model/fruitfly_R10D0SUP.csv
longbow/model/fruitfly_R10G6FAST.csv
longbow/model/fruitfly_R10G6HAC.csv
longbow/model/fruitfly_R10G6SUP.csv
longbow/model/fruitfly_R9D0FAST.csv
longbow/model/fruitfly_R9D0HAC.csv
longbow/model/fruitfly_R9D0SUP.csv
longbow/model/fruitfly_R9G2.csv
longbow/model/fruitfly_R9G4FAST.csv
longbow/model/fruitfly_R9G4HAC.csv
longbow/model/fruitfly_R9G6FAST.csv
longbow/model/fruitfly_R9G6HAC.csv
longbow/model/fruitfly_R9G6SUP.csv
longbow/model/human_5kHz_R10D0FAST.csv
longbow/model/human_5kHz_R10D0HAC.csv
longbow/model/human_5kHz_R10D0SUP.csv
longbow/model/human_5kHz_R10G6FAST.csv
longbow/model/human_5kHz_R10G6HAC.csv
longbow/model/human_5kHz_R10G6SUP.csv
longbow/model/human_R10D0FAST.csv
longbow/model/human_R10D0HAC.csv
longbow/model/human_R10D0SUP.csv
longbow/model/human_R10G6FAST.csv
longbow/model/human_R10G6HAC.csv
longbow/model/human_R10G6SUP.csv
longbow/model/human_R9D0FAST.csv
longbow/model/human_R9D0HAC.csv
longbow/model/human_R9D0SUP.csv
longbow/model/human_R9G2.csv
longbow/model/human_R9G4FAST.csv
longbow/model/human_R9G4HAC.csv
longbow/model/human_R9G6FAST.csv
longbow/model/human_R9G6HAC.csv
longbow/model/human_R9G6SUP.csv
epg_longbow-2.3.1.dist-info/LICENSE
epg_longbow-2.3.1.dist-info/METADATA
epg_longbow-2.3.1.dist-info/WHEEL
epg_longbow-2.3.1.dist-info/entry_points.txt
epg_longbow-2.3.1.dist-info/top_level.txt
epg_longbow-2.3.1.dist-info/RECORD
