Metadata-Version: 2.1
Name: epg-longbow
Version: 2.3.1
Summary: A Python program for nanopore sequencing basecalling configuration prediction
Home-page: https://github.com/JMencius/longbow
Author: Jun Mencius
Author-email: zjmeng22@m.fudan.edu.cn
Keywords: longbow,ont,configuration
Requires-Python: >=3.7
License-File: LICENSE
Requires-Dist: pyfastx (>=2.0.2)
Requires-Dist: statsmodels (>=0.13.5)
Requires-Dist: numpy (>=1.21.6)
Requires-Dist: psutil
Requires-Dist: pytest
Provides-Extra: dev
Requires-Dist: pytest ; extra == 'dev'
